pyboss/__init__.py
pyboss/boss.py
pyboss/value.py
pyboss/source/__init__.py
pyboss/source/base.py
pyboss/source/environ.py
pyboss/source/json_file.py
pyboss/source/mongodb.py
pyboss/source/redis.py
pyboss/source/yaml_file.py
pyboss-0.0.6.dist-info/METADATA
pyboss-0.0.6.dist-info/WHEEL
pyboss-0.0.6.dist-info/top_level.txt
pyboss-0.0.6.dist-info/RECORD
